bank_python/__init__.py
bank_python/classes.py
bank_python/main.py
bank_python-0.0.2.dist-info/METADATA
bank_python-0.0.2.dist-info/WHEEL
bank_python-0.0.2.dist-info/top_level.txt
bank_python-0.0.2.dist-info/RECORD
