Metadata-Version: 2.1
Name: bank-python
Version: 0.0.2
Summary: Um sistema bancário simples em Python
Home-page: https://github.com/eigiihs/bank_python_package
Author: Giovanna Sousa
Author-email: 19giihsousa@gmail.com
